{"cameraMode":{"drawMode":0,"name":"Shaded","section":"Shading Mode"},"sceneLighting":false,"audioPlay":false,"sceneViewState":{"m_AlwaysRefresh":false,"showFog":true,"showSkybox":false,"showFlares":true,"showImageEffects":true,"showParticleSystems":true,"showVisualEffectGraphs":true,"m_FxEnabled":false},"in2DMode":false,"pivot":{"x":0.3725091814994812,"y":3.293642044067383,"z":0.29306381940841677},"rotation":{"x":-0.06746146082878113,"y":-0.8013973236083984,"z":0.09197995066642761,"w":-0.587226390838623},"size":1.524450421333313,"orthographic":false}